{
  "ticker": "KXOSCARNOMPIC-26-ZOO",
  "event_ticker": "KXOSCARNOMPIC-26",
  "market_type": "binary",
  "title": "2026 Best Picture Oscar nominations?",
  "subtitle": "Zootopia 2::",
  "yes_sub_title": "Zootopia 2",
  "no_sub_title": "Zootopia 2",
  "open_time": "2025-03-10T14:00:00Z",
  "close_time": "2026-12-31T15:00:00Z",
  "expected_expiration_time": "2026-02-22T15:00:00Z",
  "expiration_time": "2026-12-31T15:00:00Z",
  "latest_expiration_time": "2026-12-31T15:00:00Z",
  "settlement_timer_seconds": 3600,
  "status": "active",
  "response_price_units": "usd_cent",
  "notional_value": 100,
  "tick_size": 1,
  "yes_bid": 1,
  "yes_ask": 10,
  "no_bid": 90,
  "no_ask": 99,
  "last_price": 0,
  "previous_yes_bid": 1,
  "previous_yes_ask": 10,
  "previous_price": 0,
  "volume": 0,
  "volume_24h": 0,
  "liquidity": 18461201,
  "open_interest": 0,
  "result": "",
  "can_close_early": true,
  "expiration_value": "",
  "category": "",
  "risk_limit_cents": 0,
  "strike_type": "custom",
  "custom_strike": {
    "Nominee": "Zootopia 2"
  },
  "rules_primary": "If Zootopia 2 has been nominated for Best Picture at the 98th Academy Awards, then the market resolves to Yes.",
  "rules_secondary": "The 98th Academy Awards Nominations are expected to be announced in January 2025.",
  "fetch_timestamp": "2025-03-27T16:55:53Z"
}